nhlscraper/__init__.py
nhlscraper/filters.py
nhlscraper/gametime.py
nhlscraper/nhlapi.py
nhlscraper/nhlscraper.py
nhlscraper/test.py
nhlscraper/utilities.py
nhlscraper/containers/__init__.py
nhlscraper/containers/faceoffs.py
nhlscraper/containers/goals.py
nhlscraper/containers/hits.py
nhlscraper/containers/penalties.py
nhlscraper/containers/shift.py
nhlscraper/containers/shootouts.py
nhlscraper/containers/shots.py
nhlscraper/containers/turnovers.py
nhlscraper-0.1.3.dist-info/DESCRIPTION.rst
nhlscraper-0.1.3.dist-info/METADATA
nhlscraper-0.1.3.dist-info/RECORD
nhlscraper-0.1.3.dist-info/WHEEL
nhlscraper-0.1.3.dist-info/dependency_links.txt
nhlscraper-0.1.3.dist-info/metadata.json
nhlscraper-0.1.3.dist-info/top_level.txt
