Metadata-Version: 2.0
Name: nhlscraper
Version: 0.1.3
Summary: NHL Scraper API for Python
Home-page: https://gitlab.com/hrel3/nhlscraper
Author: Justin Barber
Author-email: justin@hrel.ca
License: UNKNOWN
Platform: UNKNOWN
Requires-Python: >=3.6
Requires-Dist: nhlscrapi
Requires-Dist: requests (==2.13.0)
